module_hot_loading/__init__.py
module_hot_loading-0.0.1.dist-info/METADATA
module_hot_loading-0.0.1.dist-info/WHEEL
module_hot_loading-0.0.1.dist-info/licenses/LICENSE
module_hot_loading-0.0.1.dist-info/RECORD
