Metadata-Version: 2.1
Name: module-hot-loading
Version: 0.0.1
Summary: python module hot loading code
Project-URL: Homepage, https://github.com/kanadeblisst00/module_hot_loading
Project-URL: Bug Tracker, https://github.com/kanadeblisst00/module_hot_loading/issues
Author-email: kanadeblisst <kanade@blisst.cn>
License: Copyright (c) 2018 The Python Packaging Authority
License-File: LICENSE
Classifier: License :: OSI Approved :: MIT License
Classifier: Programming Language :: Python :: 3
Requires-Python: >=3.7
Requires-Dist: watchdog==3.0.0
